tmd/__init__.py
tmd/argument_parser.py
tmd/conf.py
tmd/const.py
tmd/corrector.py
tmd/exceptions.py
tmd/logs.py
tmd/types.py
tmd/ui.py
tmd/utils.py
tmd/entrypoints/__init__.py
tmd/entrypoints/alias.py
tmd/entrypoints/fix_command.py
tmd/entrypoints/main.py
tmd/entrypoints/not_configured.py
tmd/entrypoints/shell_logger.py
tmd/output_readers/__init__.py
tmd/output_readers/read_log.py
tmd/output_readers/rerun.py
tmd/output_readers/shell_logger.py
tmd/rules/__init__.py
tmd/rules/adb_unknown_command.py
tmd/rules/ag_literal.py
tmd/rules/apt_get.py
tmd/rules/apt_get_search.py
tmd/rules/apt_invalid_operation.py
tmd/rules/apt_list_upgradable.py
tmd/rules/apt_upgrade.py
tmd/rules/aws_cli.py
tmd/rules/az_cli.py
tmd/rules/brew_cask_dependency.py
tmd/rules/brew_install.py
tmd/rules/brew_link.py
tmd/rules/brew_reinstall.py
tmd/rules/brew_uninstall.py
tmd/rules/brew_unknown_command.py
tmd/rules/brew_update_formula.py
tmd/rules/cargo.py
tmd/rules/cargo_no_command.py
tmd/rules/cat_dir.py
tmd/rules/cd_correction.py
tmd/rules/cd_cs.py
tmd/rules/cd_mkdir.py
tmd/rules/cd_parent.py
tmd/rules/chmod_x.py
tmd/rules/choco_install.py
tmd/rules/composer_not_command.py
tmd/rules/conda_mistype.py
tmd/rules/cp_create_destination.py
tmd/rules/cp_omitting_directory.py
tmd/rules/cpp11.py
tmd/rules/dirty_untar.py
tmd/rules/dirty_unzip.py
tmd/rules/django_south_ghost.py
tmd/rules/django_south_merge.py
tmd/rules/dnf_no_such_command.py
tmd/rules/docker_image_being_used_by_container.py
tmd/rules/docker_login.py
tmd/rules/docker_not_command.py
tmd/rules/dry.py
tmd/rules/fab_command_not_found.py
tmd/rules/fix_alt_space.py
tmd/rules/fix_file.py
tmd/rules/gem_unknown_command.py
tmd/rules/git_add.py
tmd/rules/git_add_force.py
tmd/rules/git_bisect_usage.py
tmd/rules/git_branch_0flag.py
tmd/rules/git_branch_delete.py
tmd/rules/git_branch_delete_checked_out.py
tmd/rules/git_branch_exists.py
tmd/rules/git_branch_list.py
tmd/rules/git_checkout.py
tmd/rules/git_clone_git_clone.py
tmd/rules/git_clone_missing.py
tmdsb-0.1.2.dist-info/LICENSE.md
tmdsb-0.1.2.dist-info/METADATA
tmdsb-0.1.2.dist-info/WHEEL
tmdsb-0.1.2.dist-info/entry_points.txt
tmdsb-0.1.2.dist-info/top_level.txt
tmdsb-0.1.2.dist-info/RECORD
