Metadata-Version: 2.1
Name: tmdsb
Version: 0.1.2
Summary: 他妈的 - 一个能修正你之前控制台命令的牛逼应用
Home-page: https://github.com/violettoolssite/tmd
Author: Vladimir Iakovlev
Author-email: nvbn.rm@gmail.com
License: MIT
Requires-Python: >=2.7, !=3.0.*, !=3.1.*, !=3.2.*, !=3.3.*, !=3.4.*
Requires-Dist: colorama
Requires-Dist: psutil
Requires-Dist: six
Requires-Dist: backports.shutil-get-terminal-size ; python_version<"3.3"
Requires-Dist: pathlib2 ; python_version<"3.4"
Requires-Dist: decorator <5 ; python_version<="2.7"
Requires-Dist: pyte <0.8.1 ; python_version<="2.7"
Requires-Dist: decorator ; python_version>"2.7"
Requires-Dist: pyte ; python_version>"2.7"
Requires-Dist: win-unicode-console ; sys_platform=='win32'
